{
    "trains": [
        {
            "operation_number": 58,
            "operation_serial_number": 1,
            "kind": "特",
            "train_kind": 5,
            "delay_time": 0,
            "line_id": 26002,
            "num_of_cars": "10",
            "train_line_id": 26001,
            "station_id": null,
            "section_id": 10,
            "track_number": null,
            "up": true,
            "train_orchestration_number": "01",
            "affiliation": "急",
            "train_number": "00580620",
            "destination_station_code": 33
        },
        {
            "operation_number": 437,
            "operation_serial_number": 1,
            "kind": "普",
            "train_kind": 2,
            "delay_time": 0,
            "line_id": 26002,
            "num_of_cars": "8",
            "train_line_id": 26002,
            "station_id": null,
            "section_id": 51,
            "track_number": null,
            "up": true,
            "train_orchestration_number": "05",
            "affiliation": "都",
            "train_number": "04370620",
            "destination_station_code": 54
        },
        {
            "operation_number": 2,
            "operation_serial_number": 1,
            "kind": "普",
            "train_kind": 2,
            "delay_time": 0,
            "line_id": 26002,
            "num_of_cars": "8",
            "train_line_id": 26001,
            "station_id": null,
            "section_id": 13,
            "track_number": null,
            "up": true,
            "train_orchestration_number": "62",
            "affiliation": "急",
            "train_number": "00020520",
            "destination_station_code": 33
        },
        {
            "operation_number": 204,
            "operation_serial_number": 1,
            "kind": "普",
            "train_kind": 2,
            "delay_time": 0,
            "line_id": 26002,
            "num_of_cars": "8",
            "train_line_id": 26002,
            "station_id": 918,
            "section_id": null,
            "track_number": -1,
            "up": false,
            "train_orchestration_number": "01",
            "affiliation": "急",
            "train_number": "02040610",
            "destination_station_code": 111
        },
        {
            "operation_number": 443,
            "operation_serial_number": 1,
            "kind": "普",
            "train_kind": 2,
            "delay_time": 0,
            "line_id": 26002,
            "num_of_cars": "8",
            "train_line_id": 26002,
            "station_id": 24,
            "section_id": null,
            "track_number": -1,
            "up": false,
            "train_orchestration_number": "12",
            "affiliation": "都",
            "train_number": "04430610",
            "destination_station_code": 90
        },
        {
            "operation_number": 709,
            "operation_serial_number": 1,
            "kind": "普",
            "train_kind": 2,
            "delay_time": 0,
            "line_id": 26002,
            "num_of_cars": "8",
            "train_line_id": 26001,
            "station_id": 915,
            "section_id": null,
            "track_number": -2,
            "up": false,
            "train_orchestration_number": "84",
            "affiliation": "副",
            "train_number": "07090610",
            "destination_station_code": 103
        },
        {
            "operation_number": 641,
            "operation_serial_number": 1,
            "kind": "普",
            "train_kind": 2,
            "delay_time": 0,
            "line_id": 26002,
            "num_of_cars": "8",
            "train_line_id": 26002,
            "station_id": 24,
            "section_id": null,
            "track_number": 1,
            "up": true,
            "train_orchestration_number": "07",
            "affiliation": "相",
            "train_number": "06410620",
            "destination_station_code": 54
        },
        {
            "operation_number": 582,
            "operation_serial_number": 1,
            "kind": "普",
            "train_kind": 2,
            "delay_time": 1,
            "line_id": 26002,
            "num_of_cars": "6",
            "train_line_id": 26002,
            "station_id": 915,
            "section_id": null,
            "track_number": -1,
            "up": false,
            "train_orchestration_number": "08",
            "affiliation": "南",
            "train_number": "05820610",
            "destination_station_code": 90
        },
        {
            "operation_number": 17,
            "operation_serial_number": 1,
            "kind": "普",
            "train_kind": 2,
            "delay_time": 0,
            "line_id": 26002,
            "num_of_cars": "8",
            "train_line_id": 26001,
            "station_id": null,
            "section_id": 8,
            "track_number": null,
            "up": true,
            "train_orchestration_number": "59",
            "affiliation": "急",
            "train_number": "00170620",
            "destination_station_code": 33
        },
        {
            "operation_number": 3,
            "operation_serial_number": 1,
            "kind": "普",
            "train_kind": 2,
            "delay_time": 0,
            "line_id": 26002,
            "num_of_cars": "8",
            "train_line_id": 26001,
            "station_id": 57,
            "section_id": null,
            "track_number": 2,
            "up": true,
            "train_orchestration_number": "81",
            "affiliation": "み",
            "train_number": "00030620",
            "destination_station_code": 78
        },
        {
            "operation_number": 999,
            "operation_serial_number": 1,
            "kind": null,
            "train_kind": null,
            "delay_time": 0,
            "line_id": 26002,
            "num_of_cars": "8",
            "train_line_id": 26002,
            "station_id": 930,
            "section_id": null,
            "track_number": 2,
            "up": true,
            "train_orchestration_number": "03",
            "affiliation": "急",
            "train_number": "09990000",
            "destination_station_code": 0
        },
        {
            "operation_number": 21,
            "operation_serial_number": 1,
            "kind": "普",
            "train_kind": 2,
            "delay_time": 0,
            "line_id": 26002,
            "num_of_cars": "8",
            "train_line_id": 26001,
            "station_id": null,
            "section_id": 35,
            "track_number": null,
            "up": false,
            "train_orchestration_number": "63",
            "affiliation": "急",
            "train_number": "00210610",
            "destination_station_code": 103
        },
        {
            "operation_number": 360,
            "operation_serial_number": 1,
            "kind": "普",
            "train_kind": 2,
            "delay_time": 0,
            "line_id": 26002,
            "num_of_cars": "8",
            "train_line_id": 26002,
            "station_id": null,
            "section_id": 54,
            "track_number": null,
            "up": true,
            "train_orchestration_number": "11",
            "affiliation": "南",
            "train_number": "03600620",
            "destination_station_code": 67
        },
        {
            "operation_number": 332,
            "operation_serial_number": 1,
            "kind": "普",
            "train_kind": 2,
            "delay_time": 0,
            "line_id": 26002,
            "num_of_cars": "8",
            "train_line_id": 26002,
            "station_id": 930,
            "section_id": null,
            "track_number": -2,
            "up": false,
            "train_orchestration_number": "12",
            "affiliation": "南",
            "train_number": "03320610",
            "destination_station_code": 108
        },
        {
            "operation_number": 222,
            "operation_serial_number": 1,
            "kind": "急",
            "train_kind": 4,
            "delay_time": 1,
            "line_id": 26002,
            "num_of_cars": "8",
            "train_line_id": 26002,
            "station_id": null,
            "section_id": 61,
            "track_number": null,
            "up": false,
            "train_orchestration_number": "21",
            "affiliation": "急",
            "train_number": "02220610",
            "destination_station_code": 111
        }
    ],
    "delays": null
}