{
    "trains": [
        {
            "operation_number": 13,
            "operation_serial_number": 1,
            "kind": "普",
            "train_kind": 2,
            "delay_time": 0,
            "line_id": 26001,
            "num_of_cars": "8",
            "train_line_id": 26001,
            "station_id": null,
            "section_id": 27,
            "track_number": null,
            "up": false,
            "train_orchestration_number": "78",
            "affiliation": "急",
            "train_number": "00131310",
            "destination_station_code": 103
        },
        {
            "operation_number": 713,
            "operation_serial_number": 1,
            "kind": "普",
            "train_kind": 2,
            "delay_time": 0,
            "line_id": 26001,
            "num_of_cars": "8",
            "train_line_id": 26001,
            "station_id": 5,
            "section_id": null,
            "track_number": -1,
            "up": false,
            "train_orchestration_number": "89",
            "affiliation": "副",
            "train_number": "07131310",
            "destination_station_code": 103
        },
        {
            "operation_number": 453,
            "operation_serial_number": 1,
            "kind": "普",
            "train_kind": 2,
            "delay_time": 0,
            "line_id": 26001,
            "num_of_cars": "6",
            "train_line_id": 26002,
            "station_id": 918,
            "section_id": null,
            "track_number": -1,
            "up": false,
            "train_orchestration_number": "54",
            "affiliation": "都",
            "train_number": "04531310",
            "destination_station_code": 90
        },
        {
            "operation_number": 704,
            "operation_serial_number": 1,
            "kind": "普",
            "train_kind": 2,
            "delay_time": 0,
            "line_id": 26001,
            "num_of_cars": "8",
            "train_line_id": 26001,
            "station_id": 924,
            "section_id": null,
            "track_number": 1,
            "up": true,
            "train_orchestration_number": "93",
            "affiliation": "副",
            "train_number": "07041320",
            "destination_station_code": 33
        },
        {
            "operation_number": 8,
            "operation_serial_number": 1,
            "kind": "普",
            "train_kind": 2,
            "delay_time": 0,
            "line_id": 26001,
            "num_of_cars": "8",
            "train_line_id": 26001,
            "station_id": 913,
            "section_id": null,
            "track_number": 1,
            "up": true,
            "train_orchestration_number": "58",
            "affiliation": "急",
            "train_number": "00081320",
            "destination_station_code": 33
        },
        {
            "operation_number": 992,
            "operation_serial_number": 1,
            "kind": "急",
            "train_kind": 4,
            "delay_time": 0,
            "line_id": 26001,
            "num_of_cars": "10",
            "train_line_id": 26001,
            "station_id": 909,
            "section_id": null,
            "track_number": 1,
            "up": true,
            "train_orchestration_number": "06",
            "affiliation": "相",
            "train_number": "09921320",
            "destination_station_code": 33
        },
        {
            "operation_number": 5,
            "operation_serial_number": 1,
            "kind": "急",
            "train_kind": 4,
            "delay_time": 0,
            "line_id": 26001,
            "num_of_cars": "8",
            "train_line_id": 26001,
            "station_id": null,
            "section_id": 6,
            "track_number": null,
            "up": true,
            "train_orchestration_number": "82",
            "affiliation": "み",
            "train_number": "00051320",
            "destination_station_code": 78
        },
        {
            "operation_number": 60,
            "operation_serial_number": 1,
            "kind": "Ｆ",
            "train_kind": 7,
            "delay_time": 0,
            "line_id": 26001,
            "num_of_cars": "10",
            "train_line_id": 26001,
            "station_id": null,
            "section_id": 36,
            "track_number": null,
            "up": false,
            "train_orchestration_number": "02",
            "affiliation": "急",
            "train_number": "00601310",
            "destination_station_code": 103
        },
        {
            "operation_number": 19,
            "operation_serial_number": 1,
            "kind": "急",
            "train_kind": 4,
            "delay_time": 0,
            "line_id": 26001,
            "num_of_cars": "8",
            "train_line_id": 26001,
            "station_id": 915,
            "section_id": null,
            "track_number": -2,
            "up": false,
            "train_orchestration_number": "87",
            "affiliation": "副",
            "train_number": "00191310",
            "destination_station_code": 103
        },
        {
            "operation_number": 14,
            "operation_serial_number": 1,
            "kind": "普",
            "train_kind": 2,
            "delay_time": 0,
            "line_id": 26001,
            "num_of_cars": "8",
            "train_line_id": 26001,
            "station_id": null,
            "section_id": 13,
            "track_number": null,
            "up": true,
            "train_orchestration_number": "71",
            "affiliation": "急",
            "train_number": "00141320",
            "destination_station_code": 78
        },
        {
            "operation_number": 3,
            "operation_serial_number": 1,
            "kind": "普",
            "train_kind": 2,
            "delay_time": 0,
            "line_id": 26001,
            "num_of_cars": "8",
            "train_line_id": 26001,
            "station_id": 914,
            "section_id": null,
            "track_number": 2,
            "up": true,
            "train_orchestration_number": "83",
            "affiliation": "み",
            "train_number": "00031320",
            "destination_station_code": 33
        },
        {
            "operation_number": 2,
            "operation_serial_number": 1,
            "kind": "普",
            "train_kind": 2,
            "delay_time": 0,
            "line_id": 26001,
            "num_of_cars": "8",
            "train_line_id": 26001,
            "station_id": 908,
            "section_id": null,
            "track_number": 1,
            "up": true,
            "train_orchestration_number": "52",
            "affiliation": "急",
            "train_number": "00021320",
            "destination_station_code": 33
        },
        {
            "operation_number": 217,
            "operation_serial_number": 1,
            "kind": "急",
            "train_kind": 4,
            "delay_time": 0,
            "line_id": 26001,
            "num_of_cars": "8",
            "train_line_id": 26002,
            "station_id": 914,
            "section_id": null,
            "track_number": 1,
            "up": true,
            "train_orchestration_number": "04",
            "affiliation": "急",
            "train_number": "02171320",
            "destination_station_code": 54
        },
        {
            "operation_number": 586,
            "operation_serial_number": 1,
            "kind": "急",
            "train_kind": 4,
            "delay_time": 0,
            "line_id": 26001,
            "num_of_cars": "6",
            "train_line_id": 26002,
            "station_id": null,
            "section_id": 68,
            "track_number": null,
            "up": false,
            "train_orchestration_number": "09",
            "affiliation": "南",
            "train_number": "05861310",
            "destination_station_code": 108
        },
        {
            "operation_number": 17,
            "operation_serial_number": 1,
            "kind": "普",
            "train_kind": 2,
            "delay_time": 0,
            "line_id": 26001,
            "num_of_cars": "8",
            "train_line_id": 26001,
            "station_id": null,
            "section_id": 24,
            "track_number": null,
            "up": false,
            "train_orchestration_number": "60",
            "affiliation": "急",
            "train_number": "00171310",
            "destination_station_code": 103
        },
        {
            "operation_number": 16,
            "operation_serial_number": 1,
            "kind": "急",
            "train_kind": 4,
            "delay_time": 0,
            "line_id": 26001,
            "num_of_cars": "8",
            "train_line_id": 26001,
            "station_id": null,
            "section_id": 15,
            "track_number": null,
            "up": true,
            "train_orchestration_number": "51",
            "affiliation": "急",
            "train_number": "00161320",
            "destination_station_code": 33
        },
        {
            "operation_number": 803,
            "operation_serial_number": 1,
            "kind": "Ｆ",
            "train_kind": 7,
            "delay_time": 0,
            "line_id": 26001,
            "num_of_cars": "10",
            "train_line_id": 26001,
            "station_id": null,
            "section_id": 11,
            "track_number": null,
            "up": true,
            "train_orchestration_number": "76",
            "affiliation": "東",
            "train_number": "08031320",
            "destination_station_code": 33
        },
        {
            "operation_number": 20,
            "operation_serial_number": 1,
            "kind": "普",
            "train_kind": 2,
            "delay_time": 0,
            "line_id": 26001,
            "num_of_cars": "8",
            "train_line_id": 26001,
            "station_id": 108,
            "section_id": null,
            "track_number": -2,
            "up": false,
            "train_orchestration_number": "62",
            "affiliation": "急",
            "train_number": "00201310",
            "destination_station_code": 103
        },
        {
            "operation_number": 18,
            "operation_serial_number": 1,
            "kind": "急",
            "train_kind": 4,
            "delay_time": 0,
            "line_id": 26001,
            "num_of_cars": "8",
            "train_line_id": 26001,
            "station_id": 923,
            "section_id": null,
            "track_number": -1,
            "up": false,
            "train_orchestration_number": "63",
            "affiliation": "急",
            "train_number": "00181310",
            "destination_station_code": 103
        },
        {
            "operation_number": 771,
            "operation_serial_number": 1,
            "kind": "Ｆ",
            "train_kind": 7,
            "delay_time": 0,
            "line_id": 26001,
            "num_of_cars": "10",
            "train_line_id": 26001,
            "station_id": 5,
            "section_id": null,
            "track_number": 1,
            "up": true,
            "train_orchestration_number": "70",
            "affiliation": "副",
            "train_number": "07711320",
            "destination_station_code": 33
        },
        {
            "operation_number": 6,
            "operation_serial_number": 1,
            "kind": "普",
            "train_kind": 2,
            "delay_time": 0,
            "line_id": 26001,
            "num_of_cars": "8",
            "train_line_id": 26001,
            "station_id": null,
            "section_id": 30,
            "track_number": null,
            "up": false,
            "train_orchestration_number": "72",
            "affiliation": "急",
            "train_number": "00061310",
            "destination_station_code": 103
        },
        {
            "operation_number": 785,
            "operation_serial_number": 1,
            "kind": "Ｆ",
            "train_kind": 7,
            "delay_time": 0,
            "line_id": 26001,
            "num_of_cars": "10",
            "train_line_id": 26001,
            "station_id": null,
            "section_id": 25,
            "track_number": null,
            "up": false,
            "train_orchestration_number": "48",
            "affiliation": "副",
            "train_number": "07851310",
            "destination_station_code": 103
        },
        {
            "operation_number": 715,
            "operation_serial_number": 1,
            "kind": "普",
            "train_kind": 2,
            "delay_time": 0,
            "line_id": 26001,
            "num_of_cars": "8",
            "train_line_id": 26001,
            "station_id": null,
            "section_id": 16,
            "track_number": null,
            "up": true,
            "train_orchestration_number": "83",
            "affiliation": "副",
            "train_number": "07151320",
            "destination_station_code": 33
        },
        {
            "operation_number": 991,
            "operation_serial_number": 1,
            "kind": "急",
            "train_kind": 4,
            "delay_time": 0,
            "line_id": 26001,
            "num_of_cars": "10",
            "train_line_id": 26001,
            "station_id": null,
            "section_id": 29,
            "track_number": null,
            "up": false,
            "train_orchestration_number": "03",
            "affiliation": "相",
            "train_number": "09911310",
            "destination_station_code": 111
        },
        {
            "operation_number": 22,
            "operation_serial_number": 1,
            "kind": "普",
            "train_kind": 2,
            "delay_time": 0,
            "line_id": 26001,
            "num_of_cars": "8",
            "train_line_id": 26001,
            "station_id": 57,
            "section_id": null,
            "track_number": -2,
            "up": false,
            "train_orchestration_number": "70",
            "affiliation": "急",
            "train_number": "00221310",
            "destination_station_code": 103
        },
        {
            "operation_number": 441,
            "operation_serial_number": 1,
            "kind": "普",
            "train_kind": 2,
            "delay_time": 0,
            "line_id": 26001,
            "num_of_cars": "6",
            "train_line_id": 26002,
            "station_id": 919,
            "section_id": null,
            "track_number": 1,
            "up": true,
            "train_orchestration_number": "46",
            "affiliation": "都",
            "train_number": "04411320",
            "destination_station_code": 54
        },
        {
            "operation_number": 21,
            "operation_serial_number": 1,
            "kind": "普",
            "train_kind": 2,
            "delay_time": 0,
            "line_id": 26001,
            "num_of_cars": "8",
            "train_line_id": 26001,
            "station_id": 921,
            "section_id": null,
            "track_number": -1,
            "up": false,
            "train_orchestration_number": "39",
            "affiliation": "急",
            "train_number": "00211310",
            "destination_station_code": 103
        },
        {
            "operation_number": 588,
            "operation_serial_number": 1,
            "kind": "普",
            "train_kind": 2,
            "delay_time": 0,
            "line_id": 26001,
            "num_of_cars": "6",
            "train_line_id": 26002,
            "station_id": 916,
            "section_id": null,
            "track_number": 1,
            "up": true,
            "train_orchestration_number": "05",
            "affiliation": "南",
            "train_number": "05881320",
            "destination_station_code": 67
        }
    ],
    "delays": null
}