{
    "trains": [
        {
            "operation_number": 108,
            "operation_serial_number": 1,
            "kind": "急",
            "train_kind": 4,
            "delay_time": 2,
            "line_id": 26001,
            "num_of_cars": "10",
            "train_line_id": 26001,
            "station_id": 909,
            "section_id": null,
            "track_number": -1,
            "up": false,
            "train_orchestration_number": "09",
            "affiliation": "西",
            "train_number": "01081510",
            "destination_station_code": 103
        },
        {
            "operation_number": 21,
            "operation_serial_number": 1,
            "kind": "普",
            "train_kind": 2,
            "delay_time": 0,
            "line_id": 26001,
            "num_of_cars": "8",
            "train_line_id": 26001,
            "station_id": 108,
            "section_id": null,
            "track_number": 2,
            "up": true,
            "train_orchestration_number": "71",
            "affiliation": "急",
            "train_number": "00211520",
            "destination_station_code": 33
        },
        {
            "operation_number": 992,
            "operation_serial_number": 1,
            "kind": "普",
            "train_kind": 2,
            "delay_time": 0,
            "line_id": 26001,
            "num_of_cars": "10",
            "train_line_id": 26001,
            "station_id": 26,
            "section_id": null,
            "track_number": 1,
            "up": true,
            "train_orchestration_number": "03",
            "affiliation": "相",
            "train_number": "09921520",
            "destination_station_code": 33
        },
        {
            "operation_number": 62,
            "operation_serial_number": 1,
            "kind": "急",
            "train_kind": 4,
            "delay_time": 0,
            "line_id": 26001,
            "num_of_cars": "10",
            "train_line_id": 26001,
            "station_id": 919,
            "section_id": null,
            "track_number": -2,
            "up": false,
            "train_orchestration_number": "01",
            "affiliation": "急",
            "train_number": "00621510",
            "destination_station_code": 103
        },
        {
            "operation_number": 439,
            "operation_serial_number": 1,
            "kind": "普",
            "train_kind": 2,
            "delay_time": 0,
            "line_id": 26001,
            "num_of_cars": "6",
            "train_line_id": 26002,
            "station_id": 918,
            "section_id": null,
            "track_number": -1,
            "up": false,
            "train_orchestration_number": "45",
            "affiliation": "都",
            "train_number": "04391510",
            "destination_station_code": 90
        },
        {
            "operation_number": 596,
            "operation_serial_number": 1,
            "kind": "普",
            "train_kind": 2,
            "delay_time": 0,
            "line_id": 26001,
            "num_of_cars": "6",
            "train_line_id": 26002,
            "station_id": 914,
            "section_id": null,
            "track_number": -1,
            "up": false,
            "train_orchestration_number": "05",
            "affiliation": "南",
            "train_number": "05961510",
            "destination_station_code": 90
        },
        {
            "operation_number": 362,
            "operation_serial_number": 1,
            "kind": "急",
            "train_kind": 4,
            "delay_time": 0,
            "line_id": 26001,
            "num_of_cars": "6",
            "train_line_id": 26002,
            "station_id": 919,
            "section_id": null,
            "track_number": 1,
            "up": true,
            "train_orchestration_number": "01",
            "affiliation": "南",
            "train_number": "03621520",
            "destination_station_code": 67
        },
        {
            "operation_number": 6,
            "operation_serial_number": 1,
            "kind": "普",
            "train_kind": 2,
            "delay_time": 0,
            "line_id": 26001,
            "num_of_cars": "8",
            "train_line_id": 26001,
            "station_id": 57,
            "section_id": null,
            "track_number": -2,
            "up": false,
            "train_orchestration_number": "70",
            "affiliation": "急",
            "train_number": "00061510",
            "destination_station_code": 103
        },
        {
            "operation_number": 54,
            "operation_serial_number": 1,
            "kind": "急",
            "train_kind": 4,
            "delay_time": 0,
            "line_id": 26001,
            "num_of_cars": "10",
            "train_line_id": 26001,
            "station_id": 57,
            "section_id": null,
            "track_number": 2,
            "up": true,
            "train_orchestration_number": "06",
            "affiliation": "急",
            "train_number": "00541520",
            "destination_station_code": 33
        },
        {
            "operation_number": 58,
            "operation_serial_number": 1,
            "kind": "Ｆ",
            "train_kind": 7,
            "delay_time": 0,
            "line_id": 26001,
            "num_of_cars": "10",
            "train_line_id": 26001,
            "station_id": 925,
            "section_id": null,
            "track_number": -1,
            "up": false,
            "train_orchestration_number": "13",
            "affiliation": "急",
            "train_number": "00581510",
            "destination_station_code": 103
        },
        {
            "operation_number": 761,
            "operation_serial_number": 1,
            "kind": "Ｆ",
            "train_kind": 7,
            "delay_time": 0,
            "line_id": 26001,
            "num_of_cars": "10",
            "train_line_id": 26001,
            "station_id": null,
            "section_id": 4,
            "track_number": null,
            "up": true,
            "train_orchestration_number": "65",
            "affiliation": "副",
            "train_number": "07611520",
            "destination_station_code": 33
        },
        {
            "operation_number": 53,
            "operation_serial_number": 1,
            "kind": "Ｆ",
            "train_kind": 7,
            "delay_time": 0,
            "line_id": 26001,
            "num_of_cars": "10",
            "train_line_id": 26001,
            "station_id": null,
            "section_id": 16,
            "track_number": null,
            "up": true,
            "train_orchestration_number": "11",
            "affiliation": "急",
            "train_number": "00531520",
            "destination_station_code": 33
        },
        {
            "operation_number": 7,
            "operation_serial_number": 1,
            "kind": "普",
            "train_kind": 2,
            "delay_time": 0,
            "line_id": 26001,
            "num_of_cars": "8",
            "train_line_id": 26001,
            "station_id": 923,
            "section_id": null,
            "track_number": -1,
            "up": false,
            "train_orchestration_number": "63",
            "affiliation": "急",
            "train_number": "00071510",
            "destination_station_code": 103
        },
        {
            "operation_number": 61,
            "operation_serial_number": 1,
            "kind": "急",
            "train_kind": 4,
            "delay_time": 0,
            "line_id": 26001,
            "num_of_cars": "10",
            "train_line_id": 26001,
            "station_id": 5,
            "section_id": null,
            "track_number": 1,
            "up": true,
            "train_orchestration_number": "02",
            "affiliation": "急",
            "train_number": "00611520",
            "destination_station_code": 78
        },
        {
            "operation_number": 455,
            "operation_serial_number": 1,
            "kind": "普",
            "train_kind": 2,
            "delay_time": 0,
            "line_id": 26001,
            "num_of_cars": "6",
            "train_line_id": 26002,
            "station_id": 916,
            "section_id": null,
            "track_number": 1,
            "up": true,
            "train_orchestration_number": "21",
            "affiliation": "都",
            "train_number": "04551520",
            "destination_station_code": 54
        },
        {
            "operation_number": 1,
            "operation_serial_number": 1,
            "kind": "普",
            "train_kind": 2,
            "delay_time": 0,
            "line_id": 26001,
            "num_of_cars": "8",
            "train_line_id": 26001,
            "station_id": 26,
            "section_id": null,
            "track_number": -2,
            "up": false,
            "train_orchestration_number": "60",
            "affiliation": "急",
            "train_number": "00011610",
            "destination_station_code": 103
        },
        {
            "operation_number": 56,
            "operation_serial_number": 1,
            "kind": "急",
            "train_kind": 4,
            "delay_time": 1,
            "line_id": 26001,
            "num_of_cars": "10",
            "train_line_id": 26001,
            "station_id": 915,
            "section_id": null,
            "track_number": -2,
            "up": false,
            "train_orchestration_number": "08",
            "affiliation": "急",
            "train_number": "00561510",
            "destination_station_code": 111
        },
        {
            "operation_number": 14,
            "operation_serial_number": 1,
            "kind": "普",
            "train_kind": 2,
            "delay_time": 0,
            "line_id": 26001,
            "num_of_cars": "8",
            "train_line_id": 26001,
            "station_id": 920,
            "section_id": null,
            "track_number": -1,
            "up": false,
            "train_orchestration_number": "64",
            "affiliation": "急",
            "train_number": "00141510",
            "destination_station_code": 103
        },
        {
            "operation_number": 17,
            "operation_serial_number": 1,
            "kind": "普",
            "train_kind": 2,
            "delay_time": 3,
            "line_id": 26001,
            "num_of_cars": "8",
            "train_line_id": 26001,
            "station_id": null,
            "section_id": 26,
            "track_number": null,
            "up": false,
            "train_orchestration_number": "51",
            "affiliation": "急",
            "train_number": "00171510",
            "destination_station_code": 103
        },
        {
            "operation_number": 704,
            "operation_serial_number": 1,
            "kind": "普",
            "train_kind": 2,
            "delay_time": 0,
            "line_id": 26001,
            "num_of_cars": "8",
            "train_line_id": 26001,
            "station_id": null,
            "section_id": 43,
            "track_number": null,
            "up": false,
            "train_orchestration_number": "88",
            "affiliation": "副",
            "train_number": "07041510",
            "destination_station_code": 103
        },
        {
            "operation_number": 711,
            "operation_serial_number": 1,
            "kind": "普",
            "train_kind": 2,
            "delay_time": 0,
            "line_id": 26001,
            "num_of_cars": "8",
            "train_line_id": 26001,
            "station_id": 909,
            "section_id": null,
            "track_number": 1,
            "up": true,
            "train_orchestration_number": "83",
            "affiliation": "副",
            "train_number": "07111520",
            "destination_station_code": 33
        },
        {
            "operation_number": 9,
            "operation_serial_number": 1,
            "kind": "急",
            "train_kind": 4,
            "delay_time": 0,
            "line_id": 26001,
            "num_of_cars": "8",
            "train_line_id": 26001,
            "station_id": 26,
            "section_id": null,
            "track_number": -1,
            "up": false,
            "train_orchestration_number": "76",
            "affiliation": "急",
            "train_number": "00091610",
            "destination_station_code": 103
        },
        {
            "operation_number": 4,
            "operation_serial_number": 1,
            "kind": "普",
            "train_kind": 2,
            "delay_time": 0,
            "line_id": 26001,
            "num_of_cars": "8",
            "train_line_id": 26001,
            "station_id": null,
            "section_id": 7,
            "track_number": null,
            "up": true,
            "train_orchestration_number": "75",
            "affiliation": "急",
            "train_number": "00041520",
            "destination_station_code": 33
        },
        {
            "operation_number": 755,
            "operation_serial_number": 1,
            "kind": "Ｆ",
            "train_kind": 7,
            "delay_time": 2,
            "line_id": 26001,
            "num_of_cars": "10",
            "train_line_id": 26001,
            "station_id": null,
            "section_id": 29,
            "track_number": null,
            "up": false,
            "train_orchestration_number": "57",
            "affiliation": "副",
            "train_number": "07551510",
            "destination_station_code": 103
        },
        {
            "operation_number": 3,
            "operation_serial_number": 1,
            "kind": "普",
            "train_kind": 2,
            "delay_time": 0,
            "line_id": 26001,
            "num_of_cars": "8",
            "train_line_id": 26001,
            "station_id": null,
            "section_id": 13,
            "track_number": null,
            "up": true,
            "train_orchestration_number": "82",
            "affiliation": "み",
            "train_number": "00031520",
            "destination_station_code": 33
        },
        {
            "operation_number": 344,
            "operation_serial_number": 1,
            "kind": "普",
            "train_kind": 2,
            "delay_time": 2,
            "line_id": 26001,
            "num_of_cars": "6",
            "train_line_id": 26002,
            "station_id": 914,
            "section_id": null,
            "track_number": 1,
            "up": true,
            "train_orchestration_number": "20",
            "affiliation": "南",
            "train_number": "03441520",
            "destination_station_code": 67
        },
        {
            "operation_number": 11,
            "operation_serial_number": 1,
            "kind": "普",
            "train_kind": 2,
            "delay_time": 0,
            "line_id": 26001,
            "num_of_cars": "8",
            "train_line_id": 26001,
            "station_id": 913,
            "section_id": null,
            "track_number": -1,
            "up": false,
            "train_orchestration_number": "53",
            "affiliation": "急",
            "train_number": "00111510",
            "destination_station_code": 103
        },
        {
            "operation_number": 18,
            "operation_serial_number": 1,
            "kind": "普",
            "train_kind": 2,
            "delay_time": 0,
            "line_id": 26001,
            "num_of_cars": "8",
            "train_line_id": 26001,
            "station_id": 915,
            "section_id": null,
            "track_number": 2,
            "up": true,
            "train_orchestration_number": "58",
            "affiliation": "急",
            "train_number": "00181520",
            "destination_station_code": 78
        },
        {
            "operation_number": 16,
            "operation_serial_number": 1,
            "kind": "普",
            "train_kind": 2,
            "delay_time": 0,
            "line_id": 26001,
            "num_of_cars": "8",
            "train_line_id": 26001,
            "station_id": 924,
            "section_id": null,
            "track_number": 1,
            "up": true,
            "train_orchestration_number": "74",
            "affiliation": "急",
            "train_number": "00161520",
            "destination_station_code": 33
        }
    ],
    "delays": null
}