{
    "trains": [
        {
            "operation_number": 449,
            "operation_serial_number": 1,
            "kind": "普",
            "train_kind": 2,
            "delay_time": 0,
            "line_id": 26001,
            "num_of_cars": "6",
            "train_line_id": 26002,
            "station_id": 918,
            "section_id": null,
            "track_number": -1,
            "up": false,
            "train_orchestration_number": "57",
            "affiliation": "都",
            "train_number": "04491810",
            "destination_station_code": 90
        },
        {
            "operation_number": 707,
            "operation_serial_number": 1,
            "kind": "普",
            "train_kind": 2,
            "delay_time": 0,
            "line_id": 26001,
            "num_of_cars": "8",
            "train_line_id": 26001,
            "station_id": 924,
            "section_id": null,
            "track_number": 1,
            "up": true,
            "train_orchestration_number": "87",
            "affiliation": "副",
            "train_number": "07071820",
            "destination_station_code": 78
        },
        {
            "operation_number": 13,
            "operation_serial_number": 1,
            "kind": "普",
            "train_kind": 2,
            "delay_time": 0,
            "line_id": 26001,
            "num_of_cars": "8",
            "train_line_id": 26001,
            "station_id": 919,
            "section_id": null,
            "track_number": 2,
            "up": true,
            "train_orchestration_number": "52",
            "affiliation": "急",
            "train_number": "00131820",
            "destination_station_code": 78
        },
        {
            "operation_number": 717,
            "operation_serial_number": 1,
            "kind": "普",
            "train_kind": 2,
            "delay_time": 0,
            "line_id": 26001,
            "num_of_cars": "8",
            "train_line_id": 26001,
            "station_id": 913,
            "section_id": null,
            "track_number": 1,
            "up": true,
            "train_orchestration_number": "90",
            "affiliation": "副",
            "train_number": "07171720",
            "destination_station_code": 78
        },
        {
            "operation_number": 5,
            "operation_serial_number": 1,
            "kind": "普",
            "train_kind": 2,
            "delay_time": 0,
            "line_id": 26001,
            "num_of_cars": "8",
            "train_line_id": 26001,
            "station_id": null,
            "section_id": 4,
            "track_number": null,
            "up": true,
            "train_orchestration_number": "65",
            "affiliation": "急",
            "train_number": "00051720",
            "destination_station_code": 33
        },
        {
            "operation_number": 459,
            "operation_serial_number": 1,
            "kind": "普",
            "train_kind": 2,
            "delay_time": 0,
            "line_id": 26001,
            "num_of_cars": "6",
            "train_line_id": 26002,
            "station_id": null,
            "section_id": 54,
            "track_number": null,
            "up": true,
            "train_orchestration_number": "35",
            "affiliation": "都",
            "train_number": "04591820",
            "destination_station_code": 54
        },
        {
            "operation_number": 711,
            "operation_serial_number": 1,
            "kind": "普",
            "train_kind": 2,
            "delay_time": 0,
            "line_id": 26001,
            "num_of_cars": "8",
            "train_line_id": 26001,
            "station_id": 923,
            "section_id": null,
            "track_number": -1,
            "up": false,
            "train_orchestration_number": "83",
            "affiliation": "副",
            "train_number": "07111710",
            "destination_station_code": 103
        },
        {
            "operation_number": 785,
            "operation_serial_number": 1,
            "kind": "特",
            "train_kind": 5,
            "delay_time": 0,
            "line_id": 26001,
            "num_of_cars": "10",
            "train_line_id": 26001,
            "station_id": null,
            "section_id": 16,
            "track_number": null,
            "up": true,
            "train_orchestration_number": "49",
            "affiliation": "副",
            "train_number": "07851820",
            "destination_station_code": 33
        },
        {
            "operation_number": 6,
            "operation_serial_number": 1,
            "kind": "普",
            "train_kind": 2,
            "delay_time": 0,
            "line_id": 26001,
            "num_of_cars": "8",
            "train_line_id": 26001,
            "station_id": 926,
            "section_id": null,
            "track_number": -1,
            "up": false,
            "train_orchestration_number": "70",
            "affiliation": "急",
            "train_number": "00061710",
            "destination_station_code": 103
        },
        {
            "operation_number": 57,
            "operation_serial_number": 1,
            "kind": "急",
            "train_kind": 4,
            "delay_time": 0,
            "line_id": 26001,
            "num_of_cars": "10",
            "train_line_id": 26001,
            "station_id": null,
            "section_id": 24,
            "track_number": null,
            "up": false,
            "train_orchestration_number": "12",
            "affiliation": "急",
            "train_number": "00571810",
            "destination_station_code": 111
        },
        {
            "operation_number": 701,
            "operation_serial_number": 1,
            "kind": "普",
            "train_kind": 2,
            "delay_time": 0,
            "line_id": 26001,
            "num_of_cars": "8",
            "train_line_id": 26001,
            "station_id": 915,
            "section_id": null,
            "track_number": 2,
            "up": true,
            "train_orchestration_number": "78",
            "affiliation": "急",
            "train_number": "07011720",
            "destination_station_code": 33
        },
        {
            "operation_number": 22,
            "operation_serial_number": 1,
            "kind": "普",
            "train_kind": 2,
            "delay_time": 0,
            "line_id": 26001,
            "num_of_cars": "8",
            "train_line_id": 26001,
            "station_id": 26,
            "section_id": null,
            "track_number": -1,
            "up": false,
            "train_orchestration_number": "57",
            "affiliation": "急",
            "train_number": "00221810",
            "destination_station_code": 103
        },
        {
            "operation_number": 787,
            "operation_serial_number": 1,
            "kind": "急",
            "train_kind": 4,
            "delay_time": 0,
            "line_id": 26001,
            "num_of_cars": "10",
            "train_line_id": 26001,
            "station_id": 5,
            "section_id": null,
            "track_number": 1,
            "up": true,
            "train_orchestration_number": "54",
            "affiliation": "副",
            "train_number": "07871820",
            "destination_station_code": 33
        },
        {
            "operation_number": 2,
            "operation_serial_number": 1,
            "kind": "普",
            "train_kind": 2,
            "delay_time": 0,
            "line_id": 26001,
            "num_of_cars": "8",
            "train_line_id": 26001,
            "station_id": null,
            "section_id": 28,
            "track_number": null,
            "up": false,
            "train_orchestration_number": "85",
            "affiliation": "み",
            "train_number": "00021810",
            "destination_station_code": 103
        },
        {
            "operation_number": 789,
            "operation_serial_number": 1,
            "kind": "Ｆ",
            "train_kind": 7,
            "delay_time": 0,
            "line_id": 26001,
            "num_of_cars": "10",
            "train_line_id": 26001,
            "station_id": null,
            "section_id": 30,
            "track_number": null,
            "up": false,
            "train_orchestration_number": "52",
            "affiliation": "副",
            "train_number": "07891810",
            "destination_station_code": 103
        },
        {
            "operation_number": 16,
            "operation_serial_number": 1,
            "kind": "普",
            "train_kind": 2,
            "delay_time": 1,
            "line_id": 26001,
            "num_of_cars": "8",
            "train_line_id": 26001,
            "station_id": 920,
            "section_id": null,
            "track_number": -1,
            "up": false,
            "train_orchestration_number": "74",
            "affiliation": "急",
            "train_number": "00161810",
            "destination_station_code": 103
        },
        {
            "operation_number": 51,
            "operation_serial_number": 1,
            "kind": "急",
            "train_kind": 4,
            "delay_time": 0,
            "line_id": 26001,
            "num_of_cars": "10",
            "train_line_id": 26001,
            "station_id": 908,
            "section_id": null,
            "track_number": 1,
            "up": true,
            "train_orchestration_number": "10",
            "affiliation": "急",
            "train_number": "00511720",
            "destination_station_code": 33
        },
        {
            "operation_number": 336,
            "operation_serial_number": 1,
            "kind": "普",
            "train_kind": 2,
            "delay_time": 0,
            "line_id": 26001,
            "num_of_cars": "6",
            "train_line_id": 26002,
            "station_id": null,
            "section_id": 66,
            "track_number": null,
            "up": false,
            "train_orchestration_number": "08",
            "affiliation": "南",
            "train_number": "03361810",
            "destination_station_code": 108
        },
        {
            "operation_number": 21,
            "operation_serial_number": 1,
            "kind": "急",
            "train_kind": 4,
            "delay_time": 0,
            "line_id": 26001,
            "num_of_cars": "8",
            "train_line_id": 26001,
            "station_id": 919,
            "section_id": null,
            "track_number": -2,
            "up": false,
            "train_orchestration_number": "71",
            "affiliation": "急",
            "train_number": "00211810",
            "destination_station_code": 103
        },
        {
            "operation_number": 719,
            "operation_serial_number": 1,
            "kind": "急",
            "train_kind": 4,
            "delay_time": 0,
            "line_id": 26001,
            "num_of_cars": "8",
            "train_line_id": 26001,
            "station_id": 57,
            "section_id": null,
            "track_number": 2,
            "up": true,
            "train_orchestration_number": "89",
            "affiliation": "副",
            "train_number": "07191820",
            "destination_station_code": 33
        },
        {
            "operation_number": 8,
            "operation_serial_number": 1,
            "kind": "普",
            "train_kind": 2,
            "delay_time": 0,
            "line_id": 26001,
            "num_of_cars": "8",
            "train_line_id": 26001,
            "station_id": 913,
            "section_id": null,
            "track_number": -1,
            "up": false,
            "train_orchestration_number": "62",
            "affiliation": "急",
            "train_number": "00081810",
            "destination_station_code": 103
        },
        {
            "operation_number": 813,
            "operation_serial_number": 1,
            "kind": "特",
            "train_kind": 5,
            "delay_time": 0,
            "line_id": 26001,
            "num_of_cars": "10",
            "train_line_id": 26001,
            "station_id": 911,
            "section_id": null,
            "track_number": 1,
            "up": true,
            "train_orchestration_number": "74",
            "affiliation": "東",
            "train_number": "08131820",
            "destination_station_code": 33
        },
        {
            "operation_number": 214,
            "operation_serial_number": 1,
            "kind": "急",
            "train_kind": 4,
            "delay_time": 0,
            "line_id": 26001,
            "num_of_cars": "8",
            "train_line_id": 26002,
            "station_id": 918,
            "section_id": null,
            "track_number": 1,
            "up": true,
            "train_orchestration_number": "38",
            "affiliation": "急",
            "train_number": "02141820",
            "destination_station_code": 67
        },
        {
            "operation_number": 15,
            "operation_serial_number": 1,
            "kind": "普",
            "train_kind": 2,
            "delay_time": 0,
            "line_id": 26001,
            "num_of_cars": "8",
            "train_line_id": 26001,
            "station_id": 108,
            "section_id": null,
            "track_number": 2,
            "up": true,
            "train_orchestration_number": "84",
            "affiliation": "み",
            "train_number": "00151820",
            "destination_station_code": 33
        },
        {
            "operation_number": 112,
            "operation_serial_number": 1,
            "kind": "急",
            "train_kind": 4,
            "delay_time": 0,
            "line_id": 26001,
            "num_of_cars": "10",
            "train_line_id": 26001,
            "station_id": 910,
            "section_id": null,
            "track_number": -1,
            "up": false,
            "train_orchestration_number": "86",
            "affiliation": "西",
            "train_number": "01121810",
            "destination_station_code": 103
        },
        {
            "operation_number": 704,
            "operation_serial_number": 1,
            "kind": "普",
            "train_kind": 2,
            "delay_time": 0,
            "line_id": 26001,
            "num_of_cars": "8",
            "train_line_id": 26001,
            "station_id": 918,
            "section_id": null,
            "track_number": -2,
            "up": false,
            "train_orchestration_number": "88",
            "affiliation": "副",
            "train_number": "07041810",
            "destination_station_code": 103
        },
        {
            "operation_number": 59,
            "operation_serial_number": 1,
            "kind": "普",
            "train_kind": 2,
            "delay_time": 0,
            "line_id": 26001,
            "num_of_cars": "10",
            "train_line_id": 26001,
            "station_id": 26,
            "section_id": null,
            "track_number": 1,
            "up": true,
            "train_orchestration_number": "04",
            "affiliation": "急",
            "train_number": "00591820",
            "destination_station_code": 33
        },
        {
            "operation_number": 749,
            "operation_serial_number": 1,
            "kind": "特",
            "train_kind": 5,
            "delay_time": 0,
            "line_id": 26001,
            "num_of_cars": "10",
            "train_line_id": 26001,
            "station_id": 925,
            "section_id": null,
            "track_number": -1,
            "up": false,
            "train_orchestration_number": "67",
            "affiliation": "副",
            "train_number": "07491810",
            "destination_station_code": 103
        }
    ],
    "delays": null
}